pygit/__init__.py
pygit/commit.py
pygit/decorators.py
pygit/repo.py
tests/__init__.py
tests/commit_test.py
tests/conftest.py
tests/repo_test.py
apygit-0.0.5.dist-info/METADATA
apygit-0.0.5.dist-info/WHEEL
apygit-0.0.5.dist-info/top_level.txt
apygit-0.0.5.dist-info/RECORD
